.gitignore
MANIFEST.in
README.rst
bootstrap.py
buildout.cfg
setup.py
collective/__init__.py
collective.wpadmin.egg-info/PKG-INFO
collective.wpadmin.egg-info/SOURCES.txt
collective.wpadmin.egg-info/dependency_links.txt
collective.wpadmin.egg-info/entry_points.txt
collective.wpadmin.egg-info/namespace_packages.txt
collective.wpadmin.egg-info/not-zip-safe
collective.wpadmin.egg-info/requires.txt
collective.wpadmin.egg-info/top_level.txt
collective/wpadmin/__init__.py
collective/wpadmin/configure.zcml
collective/wpadmin/i18n.py
collective/wpadmin/rebuild_i18n.sh
collective/wpadmin/settings.py
collective/wpadmin/testing.py
collective/wpadmin/utils.py
collective/wpadmin/locales/collective.wpadmin.pot
collective/wpadmin/locales/en/LC_MESSAGES/collective.wpadmin.po
collective/wpadmin/locales/fr/LC_MESSAGES/collective.wpadmin.po
collective/wpadmin/pages/__init__.py
collective/wpadmin/pages/configure.zcml
collective/wpadmin/pages/dashboard.py
collective/wpadmin/pages/edit.py
collective/wpadmin/pages/editcomments.py
collective/wpadmin/pages/edittags.py
collective/wpadmin/pages/page.py
collective/wpadmin/pages/redirect.py
collective/wpadmin/pages/upload.py
collective/wpadmin/resources/css/bootstrap-responsive.css
collective/wpadmin/resources/css/bootstrap-responsive.min.css
collective/wpadmin/resources/css/bootstrap.css
collective/wpadmin/resources/css/bootstrap.min.css
collective/wpadmin/resources/css/jquery-ui-bootstrap.css
collective/wpadmin/resources/css/wpadmin.css
collective/wpadmin/resources/img/glyphicons-halflings-white.png
collective/wpadmin/resources/img/glyphicons-halflings.png
collective/wpadmin/resources/img/ui-bg_flat_0_aaaaaa_40x100.png
collective/wpadmin/resources/img/ui-bg_glass_55_fbf9ee_1x400.png
collective/wpadmin/resources/img/ui-bg_glass_65_ffffff_1x400.png
collective/wpadmin/resources/img/ui-bg_glass_75_dadada_1x400.png
collective/wpadmin/resources/img/ui-bg_glass_75_e6e6e6_1x400.png
collective/wpadmin/resources/img/ui-bg_glass_75_ffffff_1x400.png
collective/wpadmin/resources/img/ui-bg_highlight-soft_75_cccccc_1x100.png
collective/wpadmin/resources/img/ui-bg_inset-soft_95_fef1ec_1x100.png
collective/wpadmin/resources/img/ui-icons_222222_256x240.png
collective/wpadmin/resources/img/ui-icons_2e83ff_256x240.png
collective/wpadmin/resources/img/ui-icons_454545_256x240.png
