Metadata-Version: 1.0
Name: collective.wpadmin
Version: 1.0a2
Summary: Wordpress like admin page
Home-page: https://github.com/toutpt/collective.wpadmin
Author: JeanMichel FRANCOIS aka toutpt
Author-email: toutpt@gmail.com
License: GPL
Keywords: plone
Platform: UNKNOWN
Classifier: Programming Language :: Python
Classifier: Framework :: Plone
Classifier: Framework :: Plone :: 4.0
Classifier: Framework :: Plone :: 4.1
Classifier: Framework :: Plone :: 4.2
